partner/__init__.py
partner/greet.py
partner/llm.py
partner/main.py
linking_up-0.1.1.dist-info/METADATA
linking_up-0.1.1.dist-info/WHEEL
linking_up-0.1.1.dist-info/licenses/LICENSE
linking_up-0.1.1.dist-info/RECORD
