Metadata-Version: 2.4
Name: linking-up
Version: 0.1.1
Summary: Add your description here
License-File: LICENSE
Requires-Python: >=3.13
Requires-Dist: cleo>=2.1.0
Requires-Dist: langchain-community>=0.3.13
Requires-Dist: langchain-core>=0.3.28
Requires-Dist: langchain-openai>=0.2.14
Requires-Dist: langchain>=0.3.13
Requires-Dist: langgraph>=0.2.60
Requires-Dist: openai>=1.58.1
